README.rst
ansible_importer.py
setup.py
ansible_importer.egg-info/PKG-INFO
ansible_importer.egg-info/SOURCES.txt
ansible_importer.egg-info/dependency_links.txt
ansible_importer.egg-info/top_level.txt
ansible_importer.egg-info/zip-safe
tests/__init__.py
tests/test_importing.py
tests/test_installing.py