Metadata-Version: 1.1
Name: ansible-importer
Version: 0.0.2
Summary: Small library to allow Ansible plugins/modules to be imported.
Home-page: https://github.com/nrb/ansible_importer
Author: Nolan Brubaker
Author-email: palendae@gmail.com
License: GPLv3
Platform: UNKNOWN
Classifier: License :: OSI Approved :: GNU General Public License v3 or later (GPLv3+)
Classifier: Intended Audience :: Developers
Classifier: Programming Language :: Python
Classifier: Programming Language :: Python :: 2.7
